{ "type": "FeatureCollection", "name": "place", "crs": { "type": "name", "properties": { "name": "urn:ogc:def:crs:OGC:1.3:CRS84" } }, "features": [{ "type": "Feature", "properties": { "icon": "logo_igc" }, "geometry": { "type": "Point", "coordinates": [104.268597,52.243817] } }, { "type": "Feature", "properties": { "icon": "logo_crust" }, "geometry": { "type": "Point", "coordinates": [104.270635,52.244015] } }] }
